menucli/__init__.py
menucli-2021.4.12.dist-info/LICENSE
menucli-2021.4.12.dist-info/METADATA
menucli-2021.4.12.dist-info/WHEEL
menucli-2021.4.12.dist-info/top_level.txt
menucli-2021.4.12.dist-info/RECORD
