Metadata-Version: 2.1
Name: menucli
Version: 2021.4.12
Summary: A simple command line menu module
Home-page: https://github.com/ccorsi/menucli
Author: Claudio Corsi
Author-email: clcorsi@yahoo.com
License: MIT
Platform: UNKNOWN
Classifier: Programming Language :: Python :: 3
Classifier: License :: OSI Approved :: MIT License
Classifier: Operating System :: OS Independent
Requires-Python: >=3
